01_module/04_FPGA_Verilog/verilog/5-tristate/tristate.v
module tristate_ifelse(input in, input en, output out);
  reg out;
  always @(in,en) begin
    if(en)
      out=in;
    else
      out=1'bz;
  end
endmodule

module tristate_hardwired(input in, input en, output out);
  assign out=en?in:1'bz;
endmodule


module tristate_primitive(input in, input en, output out);
  bufif1(out,in,en);
endmodule

01_course/04_FPGA_Verilog/verilog/5-tristate/testbench.v
module tristate_TB();
  reg in, en;
  wire out1,out2,out3;
  tristate_ifelse tr1(in,en,out1);
  tristate_hardwired tr2(in,en,out2);
  tristate_primitive tr3(in,en,out3);
  always #5 in=~in;
  
  initial begin
    $dumpfile("out.vcd");
    $dumpvars(1,tristate_TB);
    in=0;
    en=0;
    #20
    en=1;
    #20
    en=0;
    #20
    $finish;
  end
endmodule

01_course/04_FPGA_Verilog/verilog/5-tristate/out.vcd
$date
	Wed Aug 19 17:51:32 2020
$end
$version
	Icarus Verilog
$end
$timescale
	1s
$end
$scope module tristate_TB $end
$var wire 1 ! out3 $end
$var wire 1 " out2 $end
$var wire 1 # out1 $end
$var reg 1 $ en $end
$var reg 1 % in $end
$upscope $end
$enddefinitions $end
#0
$dumpvars
0%
0$
z#
z"
z!
$end
#5
z!
1%
#10
z!
0%
#15
z!
1%
#20
0#
0"
0%
0!
1$
#25
1#
1"
1!
1%
#30
0#
0"
0!
0%
#35
1#
1"
1!
1%
#40
z#
z"
0%
z!
0$
#45
z!
1%
#50
z!
0%
#55
z!
1%
#60
z!
0%
