01_course/04_FPGA_Verilog/verilog/FourBitAdder/half_adder.v
`timescale 1ns / 100ps

module half_adder(
    input x,
    input y,
    output Cout,
    output S
    );

  xor #5 (S,x,y);
  and #5 (Cout,x,y);

endmodule

01_course/04_FPGA_Verilog/verilog/FourBitAdder/full_adder.v
`timescale 1ns / 100ps

module full_adder(
    input A,
    input B,
    input Ci,
    output Cout,
    output S
    );

  wire P,G,H;
  half_adder  ha1(A,B,G,P);
  half_adder  ha2(P,Ci,H,S);
  or #5 (Cout,G,H);

endmodule

01_course/04_FPGA_Verilog/verilog/FourBitAdder/FourBitAdder.v
`timescale 1ns/100ps

module FourBitAdder(
    input [3:0] A,
    input [3:0] B,
    output [3:0] S,
    output Cout
    );

  wire C1,C2,C3;

  half_adder ha0(A[0], B[0]    , C1,   S[0]);
  full_adder fa1(A[1], B[1], C1, C2,   S[1]);
  full_adder fa2(A[2], B[2], C2, C3,   S[2]);
  full_adder fa3(A[3], B[3], C3, Cout, S[3]);

endmodule

01_course/04_FPGA_Verilog/verilog/FourBitAdder/testbench.v
`timescale 1ns/100ps

module FourBitAdderTB();
  reg [3:0] A;
  reg [3:0] B;
  wire [4:0] C;
  
  FourBitAdder FBA(
    .A(A),
    .B(B),
    .Cout(C[4]),
    .S(C[3:0])
    );
  
  initial begin 
    $dumpfile("test.vcd"); 
    $dumpvars(1,FourBitAdderTB);  
    #100  A=4'd3; B=4'd4;
    #100  A=4'd0; B=4'd5;
    #100  A=4'd9; B=4'd2;
    #100  A=4'd10; B=4'd10;
    #100  A=4'd15; B=4'd15;
    #100  $finish;
  end
endmodule

01_module/04_FPGA_Verilog/verilog/FourBitAdder/test.vcd
$date
	Thu Aug 20 14:26:43 2020
$end
$version
	Icarus Verilog
$end
$timescale
	100ps
$end
$scope module FourBitAdderTB $end
$var wire 5 ! C [4:0] $end
$var reg 4 " A [3:0] $end
$var reg 4 # B [3:0] $end
$upscope $end
$enddefinitions $end
#0
$dumpvars
bx #
bx "
bx !
$end
#1000
b100 #
b11 "
#1050
bx1 !
#1100
bx11 !
#1150
b0xx11 !
#1200
b0x111 !
#1300
b111 !
#2000
b101 #
b0 "
#2100
b101 !
#3000
b10 #
b1001 "
#3100
b1011 !
#4000
b1010 #
b1010 "
#4050
b1010 !
#4100
b10000 !
#4150
b10100 !
#5000
b1111 #
b1111 "
#5100
b10110 !
#5150
b11110 !
